zamtelsms
