Metadata-Version: 2.1
Name: zamtelsms
Version: 0.0.6
Summary: A small python Package for Zamtel bulk SMS API
Home-page: https://github.com/Mathewsmusukuma/zamtel-sms
Author: Mathews Musukuma
Author-email: sikaili99@gmail.com
License: MIT License
Keywords: zamtel sms package
Platform: UNKNOWN
Classifier: Development Status :: 3 - Alpha
Classifier: Intended Audience :: Developers
Classifier: Topic :: Software Development :: Build Tools
Classifier: License :: OSI Approved :: MIT License
Classifier: Programming Language :: Python :: 3.6
Classifier: Programming Language :: Python :: 3.7
Classifier: Programming Language :: Python :: 3.8
License-File: LICENSE
